{
    "Learning in a New Language": {
        "upperTriangle": "#266A4D",
        "lowerTriangle": "#F7E5EE",
        "bottomBar": "#BEBE54"
    },

    "How to Teach AI": {
        "upperTriangle": "#103D81",
        "lowerTriangle": "#FDBF12",
        "bottomBar": "#FC451E"
    },

    "The Minimalist Teacher": {
        "upperTriangle": "#AD769E",
        "lowerTriangle": "#FDBD40",
        "bottomBar": "#E6D9E3"
    },

    "Math Fact Fluency": {
        "upperTriangle": "#fdbe23",
        "lowerTriangle": "#7DD4DB",
        "bottomBar": "#FF8D1A"
    },

    "The Classroom Behavior Manual": {
        "upperTriangle": "#F16F63",
        "lowerTriangle": "#FFD340",
        "bottomBar": "#7299BB"
    },

    "The Essential 25": {
        "upperTriangle": "#AA5689",
        "lowerTriangle": "#FFD340",
        "bottomBar": "#359EAB"
    },

    "You're the Principal! Now What?": {
        "upperTriangle": "#253C45",
        "lowerTriangle": "#77C0C7",
        "bottomBar": "#FAEA2E"
    },

    "Engage the Brain": {
        "upperTriangle": "#BEACD7",
        "lowerTriangle": "#FFC633",
        "bottomBar": "#32415F"
    },

    "Five Practices for Equity-Focused School Leadership": {
        "upperTriangle": "#5E618B",
        "lowerTriangle": "#E1EBF6",
        "bottomBar": "#6AAEBA"
    },

    "Social Emotional Learning and the Brain": {
        "upperTriangle": "#b4c7ec",
        "lowerTriangle": "#D4D848",
        "bottomBar": "#5D7A9C"
    },

    "Giving Students a Say": {
        "upperTriangle": "#78CEBC",
        "lowerTriangle": "#FFD138",
        "bottomBar": "#ED7253"
    },

    "Arias Series": {
        "upperTriangle": "#7680B1",
        "lowerTriangle": "#FFAE52",
        "bottomBar": "#BE5A9A"
    },

    "Rebranding": {
        "upperTriangle": "#2D393D",
        "lowerTriangle": "#9FE2D4",
        "bottomBar": "#E89BA5"
    },

    "Author Workshops": {
        "upperTriangle": "#E56E7C",
        "lowerTriangle": "#B0E3D7",
        "bottomBar": "#2D393D"
    },

    "'Be' Ad Series": {
        "upperTriangle": "#9CC450",
        "lowerTriangle": "#B8E5EA",
        "bottomBar": "#284D5D"
    },

    "Lessons Learned Catalog": {
        "upperTriangle": "#615d6f",
        "lowerTriangle": "#FEB59F",
        "bottomBar": "#53C3BE"
    },

    "ASCD Resource Guide": {
        "upperTriangle": "#515154",
        "lowerTriangle": "#C4D041",
        "bottomBar": "#5EABC3"
    },

    "Spring Sourcebook": {
        "upperTriangle": "#2B7CCC",
        "lowerTriangle": "#57bdcc",
        "bottomBar": "#10394D"
    },

    "Trauma-Sensitive Schools Catalog": {
        "upperTriangle": "#183550",
        "lowerTriangle": "#8EB7E6",
        "bottomBar": "#B66C5F"
    },

    "Summer Catalog": {
        "upperTriangle": "#FFA536",
        "lowerTriangle": "#98D2D8",
        "bottomBar": "#FA7235"
    },

    "Membership Promotion": {
        "upperTriangle": "#B25B93",
        "lowerTriangle": "#FDBE59",
        "bottomBar": "#F44985"
    },

    "Book Bundles": {
        "upperTriangle": "#FFB98D",
        "lowerTriangle": "#C1D0EA",
        "bottomBar": "#14866D"
    },

    "Product Ad Series": {
        "upperTriangle": "#435770",
        "lowerTriangle": "#BEACD7",
        "bottomBar": "#286CC9"
    },

    "What's New?": {
        "upperTriangle": "#1B9BB4",
        "lowerTriangle": "#F0CD49",
        "bottomBar": "#4A4D52"
    },

    "Recharge & Reconnect": {
        "upperTriangle": "#044068",
        "lowerTriangle": "#FFAC27",
        "bottomBar": "#159774"
    },

    "Empower19": {
        "upperTriangle": "#FCD8E4",
        "lowerTriangle": "#A6e3eb",
        "bottomBar": "#FECF2F"
    },

    "The Adaptive Leader": {
        "upperTriangle": "#F48D95",
        "lowerTriangle": "#91D0C0",
        "bottomBar": "#2C373C"
    },

    "Empower17": {
        "upperTriangle": "#2E75AC",
        "lowerTriangle": "#F79C31",
        "bottomBar": "#CFE04F"
    },

    "Annual Conference 2023": {
        "upperTriangle": "#9A9FD0",
        "lowerTriangle": "#FFCB3E",
        "bottomBar": "#FF6E03"
    },

    "Witsby Booth": {
        "upperTriangle": "#75C4B1",
        "lowerTriangle": "#F8ECE0",
        "bottomBar": "#F37E90"
    },

    "Happiness": {
        "upperTriangle": "#A382A7",
        "lowerTriangle": "#F09D3B",
        "bottomBar": "#B2DFEA"
    },

    "Japan Postcards": {
        "upperTriangle": "#F6C005",
        "lowerTriangle": "#BDABC1",
        "bottomBar": "#2A8058"
    }
}